sphinx_json_globaltoc/__init__.py
sphinx_json_globaltoc/builders.py
sphinx_json_globaltoc/py.typed
sphinxcontrib_jsonglobaltoc-0.1.5.dist-info/LICENSE.txt
sphinxcontrib_jsonglobaltoc-0.1.5.dist-info/METADATA
sphinxcontrib_jsonglobaltoc-0.1.5.dist-info/WHEEL
sphinxcontrib_jsonglobaltoc-0.1.5.dist-info/top_level.txt
sphinxcontrib_jsonglobaltoc-0.1.5.dist-info/RECORD
