Metadata-Version: 2.1
Name: sphinxcontrib-jsonglobaltoc
Version: 0.1.5
Summary: Sphinx extension to add a global table of contents to JSON output files
Home-page: https://github.com/caltechads/sphinxcontrib-jsonglobaltoc
Author: Caltech IMSS ADS
Author-email: imss-ads-staff@caltech.edu
Project-URL: Source, https://github.com/caltechads/sphinxcontrib-jsonglobaltoc
Project-URL: Issues, https://github.com/caltechads/sphinxcontrib-jsonglobaltoc/issues
Keywords: documentation,sphinx,json
Classifier: Development Status :: 4 - Beta
Classifier: Environment :: Console
Classifier: Intended Audience :: Developers
Classifier: Operating System :: OS Independent
Classifier: Programming Language :: Python
Classifier: Programming Language :: Python :: 3
Classifier: Programming Language :: Python :: 3.7
Classifier: Programming Language :: Python :: 3.8
Classifier: Programming Language :: Python :: 3.9
Classifier: Programming Language :: Python :: 3.10
Classifier: Topic :: Documentation
Classifier: Topic :: Software Development :: Documentation
Requires-Python: >=3.7
License-File: LICENSE.txt
Requires-Dist: sphinx
Requires-Dist: sphinxcontrib-serializinghtml
